swarmauri_keyprovider_vaulttransit/VaultTransitKeyProvider.py
swarmauri_keyprovider_vaulttransit/__init__.py
swarmauri_keyprovider_vaulttransit-0.9.0.dev4.dist-info/LICENSE
swarmauri_keyprovider_vaulttransit-0.9.0.dev4.dist-info/METADATA
swarmauri_keyprovider_vaulttransit-0.9.0.dev4.dist-info/WHEEL
swarmauri_keyprovider_vaulttransit-0.9.0.dev4.dist-info/entry_points.txt
swarmauri_keyprovider_vaulttransit-0.9.0.dev4.dist-info/RECORD
