Metadata-Version: 2.3
Name: swarmauri_keyprovider_vaulttransit
Version: 0.9.0.dev4
Summary: Swarmauri Vault Transit Key Provider
License: Apache-2.0
Author: Jacob Stewart
Author-email: jacob@swarmauri.com
Requires-Python: >=3.10,<3.13
Classifier: License :: OSI Approved :: Apache Software License
Classifier: Programming Language :: Python :: 3.10
Classifier: Programming Language :: Python :: 3.11
Classifier: Programming Language :: Python :: 3.12
Provides-Extra: crypto
Provides-Extra: vault
Requires-Dist: cryptography (>=41.0.0)
Requires-Dist: cryptography (>=41.0.0) ; extra == "crypto"
Requires-Dist: hvac (>=2.1.0)
Requires-Dist: hvac (>=2.1.0) ; extra == "vault"
Requires-Dist: swarmauri_base
Requires-Dist: swarmauri_core
Requires-Dist: swarmauri_standard
